smoker/__init__.py
smoker/butt.py
smoker/joint.py
smoker-1.0.dist-info/LICENCE
smoker-1.0.dist-info/METADATA
smoker-1.0.dist-info/WHEEL
smoker-1.0.dist-info/top_level.txt
smoker-1.0.dist-info/RECORD
